MuffinTrack/MuffinTrack.py
MuffinTrack/__init__.py
MuffinTrack/__main__.py
muffintrack-1.0.3.dist-info/METADATA
muffintrack-1.0.3.dist-info/WHEEL
muffintrack-1.0.3.dist-info/RECORD
