Metadata-Version: 2.4
Name: MuffinTrack
Version: 1.0.3
Summary: A parser to convert text notes into objects to facilitate simple project management
Project-URL: Homepage, https://github.com/jstz84/MuffinTrack
Project-URL: Issues, https://github.com/jstz84/MuffinTrack/issues
Author: Jessica Stultz
License-Expression: BSD-2-Clause
Classifier: Natural Language :: English
Classifier: Operating System :: OS Independent
Classifier: Programming Language :: Python :: 3
Classifier: Topic :: Text Processing
Classifier: Topic :: Text Processing :: General
Requires-Python: >=3.9
